odoo/addons/product_list_pricelist_price/README.rst
odoo/addons/product_list_pricelist_price/__init__.py
odoo/addons/product_list_pricelist_price/__manifest__.py
odoo/addons/product_list_pricelist_price/i18n/product_list_pricelist_price.pot
odoo/addons/product_list_pricelist_price/models/__init__.py
odoo/addons/product_list_pricelist_price/models/product_pricelist.py
odoo/addons/product_list_pricelist_price/models/product_product.py
odoo/addons/product_list_pricelist_price/models/product_template.py
odoo/addons/product_list_pricelist_price/readme/CONTRIBUTORS.rst
odoo/addons/product_list_pricelist_price/readme/DESCRIPTION.rst
odoo/addons/product_list_pricelist_price/readme/USAGE.rst
odoo/addons/product_list_pricelist_price/static/description/icon.png
odoo/addons/product_list_pricelist_price/static/description/index.html
odoo/addons/product_list_pricelist_price/tests/__init__.py
odoo/addons/product_list_pricelist_price/tests/test_product_list_pricelist_price.py
odoo/addons/product_list_pricelist_price/views/product_pricelist_views.xml
odoo/addons/product_list_pricelist_price/views/product_template_views.xml
odoo/addons/product_list_pricelist_price/views/product_views.xml
odoo13_addon_product_list_pricelist_price-13.0.1.0.1.dist-info/METADATA
odoo13_addon_product_list_pricelist_price-13.0.1.0.1.dist-info/WHEEL
odoo13_addon_product_list_pricelist_price-13.0.1.0.1.dist-info/top_level.txt
odoo13_addon_product_list_pricelist_price-13.0.1.0.1.dist-info/RECORD
